setup.py
jobaggregator/__init__.py
jobaggregator.egg-info/PKG-INFO
jobaggregator.egg-info/SOURCES.txt
jobaggregator.egg-info/dependency_links.txt
jobaggregator.egg-info/top_level.txt