Metadata-Version: 2.1
Name: jobaggregator
Version: 1.0.0
Summary: Common Python package for job aggregator project
Home-page: UNKNOWN
Author: portfolio-shop
License: UNKNOWN
Platform: UNKNOWN
